LICENSE.txt
README.md
setup.cfg
setup.py
rpsgame/__init__.py
rpsgame/game.py
rpsgame/helper.py
rpsgame/logic.py
rpsgame/main.py
rpsgame.egg-info/PKG-INFO
rpsgame.egg-info/SOURCES.txt
rpsgame.egg-info/dependency_links.txt
rpsgame.egg-info/entry_points.txt
rpsgame.egg-info/not-zip-safe
rpsgame.egg-info/requires.txt
rpsgame.egg-info/top_level.txt