Metadata-Version: 1.0
Name: rpsgame
Version: 1.1
Summary: Classic game of Rock Paper and Scissors
Home-page: https://github.com/mukkund1996/RPSGame
Author: Mukkund Sunjii
Author-email: mukkundsunjii@gmail.com
License: MIT
Platform: UNKNOWN
